moa/__init__.py
moa/client.py
moa/config.py
moa/exceptions.py
moa/api/__init__.py
moa/api/graph_search.py
moa/api/memory.py
moa/api/relationships.py
moa/models/__init__.py
moa/models/base.py
moa/models/graph.py
moa/models/memory.py
moa/utils/__init__.py
moa/utils/http.py
moa_sdk-0.1.0.dist-info/METADATA
moa_sdk-0.1.0.dist-info/WHEEL
moa_sdk-0.1.0.dist-info/RECORD
